procleaner/__init__.py
procleaner/update.py
procleaner-0.0.3.dist-info/LICENSE
procleaner-0.0.3.dist-info/METADATA
procleaner-0.0.3.dist-info/WHEEL
procleaner-0.0.3.dist-info/top_level.txt
procleaner-0.0.3.dist-info/RECORD
